privacy_flow_map/__init__.py
privacy_flow_map/__main__.py
privacy_flow_map/cli.py
privacy_flow_map/compose.py
privacy_flow_map/flowmap.py
privacy_flow_map/license_manager.py
privacy_flow_map/logger.py
privacy_flow_map/parser.py
privacy_flow_map/render.py
privacy_flow_map/report_builder.py
privacy_flow_map/scan_web.py
privacyflow-2.1.0.dist-info/licenses/LICENSE
privacyflow-2.1.0.dist-info/METADATA
privacyflow-2.1.0.dist-info/WHEEL
privacyflow-2.1.0.dist-info/entry_points.txt
privacyflow-2.1.0.dist-info/top_level.txt
privacyflow-2.1.0.dist-info/RECORD
